MSCI/__init__.py
MSCI/cli.py
MSCI/Grouping_MS1/Grouping_mw_irt.py
MSCI/Grouping_MS1/__init__.py
MSCI/Preprocessing/Koina.py
MSCI/Preprocessing/Parsing.py
MSCI/Preprocessing/__init__.py
MSCI/Preprocessing/create_hla.py
MSCI/Preprocessing/filter_spectra.py
MSCI/Preprocessing/read_msp_file.py
MSCI/Preprocessing/read_mzml.py
MSCI/Similarity/__init__.py
MSCI/Similarity/spectral_angle_similarity.py
MSCI/data/__init__.py
MSCI/data/digest.py
MSCI/gui/__init__.py
MSCI/gui/landing_page.py
MSCI/gui/main.py
MSCI/gui/peptide_analysis.py
MSCI/gui/peptide_checker.py
MSCI/gui/utils.py
MSCI/mutation/__init__.py
MSCI/mutation/mutated_sequences.py
MSCI/visualization/__init__.py
MSCI/visualization/plots.py
MSCI-0.2.3.dist-info/AUTHORS.rst
MSCI-0.2.3.dist-info/LICENSE
MSCI-0.2.3.dist-info/METADATA
MSCI-0.2.3.dist-info/WHEEL
MSCI-0.2.3.dist-info/top_level.txt
MSCI-0.2.3.dist-info/RECORD
